protree/__init__.py
protree/detectors.py
protree/meta.py
protree/pruning.py
protree/transformations.py
protree/utils.py
protree/data/__init__.py
protree/data/named_stream.py
protree/data/real_stream.py
protree/data/river_generators.py
protree/data/static.py
protree/data/stream_generators.py
protree/data/utils.py
protree/explainers/__init__.py
protree/explainers/naive.py
protree/explainers/tree_distance.py
protree/explainers/utils.py
protree/metrics/__init__.py
protree/metrics/classification.py
protree/metrics/compare.py
protree/metrics/group.py
protree/metrics/individual.py
protree-0.1.2.dist-info/METADATA
protree-0.1.2.dist-info/WHEEL
protree-0.1.2.dist-info/top_level.txt
protree-0.1.2.dist-info/RECORD
