Metadata-Version: 2.4
Name: protree
Version: 0.1.2
Summary: Protree is  a set of utilities for prototype selection in tree-based models and usage of prototypes in drift detection.
Home-page: https://github.com/jkarolczak/protree
Author: jkarolczak
Author-email: jacek.karolczak@outlook.com
Classifier: Programming Language :: Python :: 3
Classifier: License :: OSI Approved :: MIT License
Classifier: Operating System :: OS Independent
Requires-Python: >=3.9
Requires-Dist: click
Requires-Dist: numpy
Requires-Dist: pandas
Requires-Dist: river
Requires-Dist: scikit-learn
Requires-Dist: scipy
Provides-Extra: all
Requires-Dist: python-mnist; extra == "all"
Requires-Dist: torch; extra == "all"
Requires-Dist: torchvision; extra == "all"
Requires-Dist: wandb; extra == "all"
Dynamic: author
Dynamic: author-email
Dynamic: classifier
Dynamic: description
Dynamic: description-content-type
Dynamic: home-page
Dynamic: provides-extra
Dynamic: requires-dist
Dynamic: requires-python
Dynamic: summary
